falconcv/__init__.py
falconcv/cons/__init__.py
falconcv/data/__init__.py
falconcv/data/coco.py
falconcv/data/openimages.py
falconcv/data/pascalvoc_annotation.py
falconcv/data/pascalvoc_dataset.py
falconcv/data/pascalvoc_image.py
falconcv/data/pascalvoc_metrics.py
falconcv/data/pascalvoc_utils.py
falconcv/data/remote_dataset.py
falconcv/data/scrapping/__init__.py
falconcv/data/scrapping/bing_scraper.py
falconcv/data/scrapping/flickr_scraper.py
falconcv/data/scrapping/scraper.py
falconcv/decor/__init__.py
falconcv/decor/cmd_depends_decor.py
falconcv/decor/depends_decor.py
falconcv/decor/exception_decor.py
falconcv/decor/path_assert.py
falconcv/decor/timeit_decor.py
falconcv/decor/type_assert_decor.py
falconcv/models/__init__.py
falconcv/models/api_installer.py
falconcv/models/api_model.py
falconcv/models/detectron/__init__.py
falconcv/models/model_builder.py
falconcv/models/toda/__init__.py
falconcv/models/toda/model_lib_v2.py
falconcv/models/toda/toda_installer.py
falconcv/models/toda/toda_pipeline_handler.py
falconcv/models/toda/toda_trainable_model.py
falconcv/models/toda/toda_trained_model.py
falconcv/models/toda/toda_zoo.py
falconcv/util/__init__.py
falconcv/util/color_utils.py
falconcv/util/datasets_utils.py
falconcv/util/file_utils.py
falconcv/util/git_utils.py
falconcv/util/image_utils.py
falconcv/util/lib_utils.py
falconcv/util/log_utils.py
falconcv/util/s3_utils.py
falconcv/util/toda_utils.py
falconcv/util/vis_utils.py
falconcv-1.0.5.dist-info/LICENSE
falconcv-1.0.5.dist-info/WHEEL
falconcv-1.0.5.dist-info/METADATA
falconcv-1.0.5.dist-info/RECORD
