Metadata-Version: 2.1
Name: falconcv
Version: 1.0.5
Summary: 
Author: Henry Ruiz
Author-email: henry.ruiz@tamu.edu
Requires-Python: >=3.7.0,<3.8.0
Classifier: Programming Language :: Python :: 3
Classifier: Programming Language :: Python :: 3.7
Requires-Dist: GitPython (>=3.1.27,<4.0.0)
Requires-Dist: Mako (>=1.2.0,<2.0.0)
Requires-Dist: Pillow (>=9.1.1,<10.0.0)
Requires-Dist: alive-progress (>=2.4.1,<3.0.0)
Requires-Dist: boto3 (>=1.24.13,<2.0.0)
Requires-Dist: bs4 (>=0.0.1,<0.0.2)
Requires-Dist: dask[complete] (==2.30.0)
Requires-Dist: lxml (>=4.9.0,<5.0.0)
Requires-Dist: matplotlib (>=3.5.2,<4.0.0)
Requires-Dist: opencv-python (>=4.6.0,<5.0.0)
Requires-Dist: pandas (<=1.3.5)
Requires-Dist: pyparsing (==2.4.2)
Requires-Dist: requests (>=2.28.0,<3.0.0)
Requires-Dist: rich (>=12.4.4,<13.0.0)
Requires-Dist: seaborn (>=0.11.2,<0.12.0)
Requires-Dist: tflite-support (>=0.4.1,<0.5.0)
Requires-Dist: typing-extensions (>=4.2.0,<5.0.0)
Requires-Dist: validators (>=0.20.0,<0.21.0)
